.gitignore
apps/.gitignore
apps/CCM_Matrix.py
apps/CrossMap_ColumnList.py
apps/CrossMap_Columns.py
apps/CrossMap_Matrix.py
apps/EDimColsBlock.py
apps/EmbedDim_Columns.py
apps/Embedding.py
apps/SMap_Tp.py
apps/SMap_theta.py
apps/tests/.gitignore
apps/tests/CLI_tests.py
apps/tests/pyEDM_apps_tests.ipynb
pyEDM/.gitignore
pyEDM/API.py
pyEDM/AuxFunc.py
pyEDM/CCM.py
pyEDM/EDM.py
pyEDM/Formatting.py
pyEDM/LoadData.py
pyEDM/Multiview.py
pyEDM/Neighbors.py
pyEDM/PoolFunc.py
pyEDM/SMap.py
pyEDM/Simplex.py
pyEDM/__init__.py
pyEDM/data/LorenzData1000.csv
pyEDM/data/S12CD-S333-SumFlow_1980-2005.csv
pyEDM/data/TentMap.csv
pyEDM/data/TentMapNoise.csv
pyEDM/data/block_3sp.csv
pyEDM/data/circle.csv
pyEDM/data/circle_noTime.csv
pyEDM/data/circle_noise.csv
pyEDM/data/columnNameSpace.csv
pyEDM/data/sardine_anchovy_sst.csv
pyEDM/tests/.gitignore
pyEDM/tests/examples.py
pyEDM/tests/smapSolverTest.py
pyEDM/tests/tests.py
pyEDM/tests/validation/CCM_Lorenz5D_MV_Space_valid.csv
pyEDM/tests/validation/CCM_Lorenz5D_MV_valid.csv
pyEDM/tests/validation/CCM_anch_sst_valid.csv
pyEDM/tests/validation/CCM_nan_valid.csv
pyEDM/tests/validation/EmbedDim_valid.csv
pyEDM/tests/validation/Multiview_combos_valid.csv
pyEDM/tests/validation/Multiview_pred_valid.csv
pyEDM/tests/validation/PredictInterval_valid.csv
pyEDM/tests/validation/PredictNonlinear_valid.csv
pyEDM/tests/validation/SMap_circle_E2_embd_valid.csv
pyEDM/tests/validation/SMap_circle_E4_valid.csv
pyEDM/tests/validation/SMap_nan_valid.csv
pyEDM/tests/validation/SMap_noTime_valid.csv
pyEDM/tests/validation/Smplx_DateTime_valid.csv
pyEDM/tests/validation/Smplx_E3_block_3sp_valid.csv
pyEDM/tests/validation/Smplx_E3_embd_block_3sp_valid.csv
pyEDM/tests/validation/Smplx_disjointLib_valid.csv
pyEDM/tests/validation/Smplx_disjointPred_nan_valid.csv
pyEDM/tests/validation/Smplx_exclRadius_valid.csv
pyEDM/tests/validation/Smplx_nan2_valid.csv
pyEDM/tests/validation/Smplx_nan_valid.csv
pyEDM/tests/validation/Smplx_negTp_block_3sp_valid.csv
pyedm-2.3.2.dist-info/METADATA
pyedm-2.3.2.dist-info/WHEEL
pyedm-2.3.2.dist-info/entry_points.txt
pyedm-2.3.2.dist-info/licenses/LICENSE
pyedm-2.3.2.dist-info/RECORD
