Metadata-Version: 2.4
Name: pyEDM
Version: 2.3.2
Summary: Python/Pandas toolset for Empirical Dynamic Modeling.
Keywords: EDM,Empirical Dynamic Modeling,nonlinear dynamics,time series,state space
Author-Email: Joseph Park <JosephPark@IEEE.org>
Maintainer-Email: Joseph Park <JosephPark@IEEE.org>
License-Expression: LicenseRef-UCSD-License
License-File: LICENSE
Classifier: Programming Language :: Python :: 3
Classifier: Operating System :: OS Independent
Project-URL: Homepage, https://deepeco.ucsd.edu/
Project-URL: Documentation, https://sugiharalab.github.io/EDM_Documentation/
Project-URL: Repository, https://github.com/SugiharaLab/pyEDM
Project-URL: Issues, https://github.com/SugiharaLab/pyEDM/issues
Requires-Python: >=3.10
Requires-Dist: numpy
Requires-Dist: scipy
Requires-Dist: scikit-learn
Requires-Dist: pandas>=2.0
Requires-Dist: matplotlib>=3.7
